MANIFEST.in
README.rst
setup.py
ITI1480A_linux.egg-info/PKG-INFO
ITI1480A_linux.egg-info/SOURCES.txt
ITI1480A_linux.egg-info/dependency_links.txt
ITI1480A_linux.egg-info/entry_points.txt
ITI1480A_linux.egg-info/requires.txt
ITI1480A_linux.egg-info/top_level.txt
iti1480a/__init__.py
iti1480a/capture.py
iti1480a/display.py
iti1480a/dump_pipe.py
iti1480a/incremental_yacc.py
iti1480a/parser.py
iti1480a/spt2hex.py
udev/ITI1480A.rules
udev/ITI1480A.sh