Metadata-Version: 1.1
Name: ITI1480A-linux
Version: 3.0
Summary: Tools for the ITI1480A usb protocol analyser
Home-page: http://github.com/vpelletier/ITI1480A-linux
Author: Vincent Pelletier
Author-email: plr.vincent@gmail.com
License: GPLv2+
Keywords: usb protocol analyser ITI1480A
Platform: any
Classifier: Intended Audience :: Information Technology
Classifier: License :: OSI Approved :: GNU General Public License v2 or later (GPLv2+)
Classifier: Operating System :: OS Independent
